{
    "message": {
        "query_graph": {
            "edges": {
                "e01": {
                    "object": "n0",
                    "subject": "n1",
                    "predicates": 
                        [
                            "biolink:prevents",
                            "biolink:negatively_regulates_entity",
                            "biolink:decreases_secretion_of",
                            "biolink:decreases_transport_of",
                            "biolink:decreases_activity_of",
                            "biolink:decreases_synthesis_of",
                            "biolink:decreases_expression_of",
                            "biolink:increases_degradation_of",
                            "biolink:entity_negatively_regulates_entity",
                            "biolink:disrupts"
                        ]
                }
            },
            "nodes": {
                "n0": {
                    "ids": [
                        "HGNC:11389"
                    ]
                },
                "n1": {
                    "categories": [
                        "biolink:ChemicalSubstance"
                    ]
                }
            }
        }
    }
}
